<?xml version="1.0" ?>
<annotation>
<folder>freckles</folder>
<filename>21416.jpg</filename>
<path>C:\Users\Administrator\Desktop\皮肤标注验证\spots\freckles\21416.jpg</path>
<source>
    <database>Unknown</database>
</source>
<size>
    <width>2448</width>
    <height>3264</height>
    <depth>3</depth>
</size>

<segmented>0</segmented>
    <object>
    <name>色素痣</name>
    <pose>Unspecified</pose>
    <truncated>0</truncated>
    <difficult>0</difficult>
    <bndbox>
        <xmin>1767</xmin>
        <ymin>1602</ymin>
        <xmax>1872</xmax>
        <ymax>1732</ymax>
    </bndbox>
</object>
    <object>
    <name>黑头</name>
    <pose>Unspecified</pose>
    <truncated>0</truncated>
    <difficult>0</difficult>
    <bndbox>
        <xmin>1156</xmin>
        <ymin>2056</ymin>
        <xmax>1366</xmax>
        <ymax>2473</ymax>
    </bndbox>
</object>
    <object>
    <name>雀斑</name>
    <pose>Unspecified</pose>
    <truncated>0</truncated>
    <difficult>0</difficult>
    <bndbox>
        <xmin>1494</xmin>
        <ymin>2038</ymin>
        <xmax>1943</xmax>
        <ymax>2378</ymax>
    </bndbox>
</object>
    <object>
    <name>雀斑</name>
    <pose>Unspecified</pose>
    <truncated>0</truncated>
    <difficult>0</difficult>
    <bndbox>
        <xmin>558</xmin>
        <ymin>2099</ymin>
        <xmax>1025</xmax>
        <ymax>2374</ymax>
    </bndbox>
</object>
</annotation>
