<?xml version="1.0" ?>
<annotation>
<folder>brown blue nevus</folder>
<filename>25277.jpg</filename>
<path>C:\Users\Administrator\Desktop\皮肤标注验证\spots\brown blue nevus\25277.jpg</path>
<source>
    <database>Unknown</database>
</source>
<size>
    <width>3024</width>
    <height>4032</height>
    <depth>3</depth>
</size>

<segmented>0</segmented>
    <object>
    <name>褐青色痣</name>
    <pose>Unspecified</pose>
    <truncated>0</truncated>
    <difficult>0</difficult>
    <bndbox>
        <xmin>2201</xmin>
        <ymin>2311</ymin>
        <xmax>2440</xmax>
        <ymax>2738</ymax>
    </bndbox>
</object>
    <object>
    <name>褐青色痣</name>
    <pose>Unspecified</pose>
    <truncated>0</truncated>
    <difficult>0</difficult>
    <bndbox>
        <xmin>683</xmin>
        <ymin>2414</ymin>
        <xmax>915</xmax>
        <ymax>2819</ymax>
    </bndbox>
</object>
</annotation>
