<?xml version="1.0" ?>
<annotation>
<folder>sunburn</folder>
<filename>25578.jpg</filename>
<path>C:\Users\Administrator\Desktop\皮肤标注验证\spots\sunburn\25578.jpg</path>
<source>
    <database>Unknown</database>
</source>
<size>
    <width>2448</width>
    <height>3264</height>
    <depth>3</depth>
</size>

<segmented>0</segmented>
    <object>
    <name>晒斑</name>
    <pose>Unspecified</pose>
    <truncated>0</truncated>
    <difficult>0</difficult>
    <bndbox>
        <xmin>1062</xmin>
        <ymin>2264</ymin>
        <xmax>1178</xmax>
        <ymax>2380</ymax>
    </bndbox>
</object>
    <object>
    <name>黄褐斑</name>
    <pose>Unspecified</pose>
    <truncated>0</truncated>
    <difficult>0</difficult>
    <bndbox>
        <xmin>1327</xmin>
        <ymin>1095</ymin>
        <xmax>1691</xmax>
        <ymax>1446</ymax>
    </bndbox>
</object>
    <object>
    <name>黄褐斑</name>
    <pose>Unspecified</pose>
    <truncated>0</truncated>
    <difficult>0</difficult>
    <bndbox>
        <xmin>685</xmin>
        <ymin>1028</ymin>
        <xmax>1131</xmax>
        <ymax>1412</ymax>
    </bndbox>
</object>
    <object>
    <name>黄褐斑</name>
    <pose>Unspecified</pose>
    <truncated>0</truncated>
    <difficult>0</difficult>
    <bndbox>
        <xmin>563</xmin>
        <ymin>2065</ymin>
        <xmax>1025</xmax>
        <ymax>2309</ymax>
    </bndbox>
</object>
    <object>
    <name>炎症性色沉着</name>
    <pose>Unspecified</pose>
    <truncated>0</truncated>
    <difficult>0</difficult>
    <bndbox>
        <xmin>979</xmin>
        <ymin>3008</ymin>
        <xmax>1294</xmax>
        <ymax>3202</ymax>
    </bndbox>
</object>
</annotation>
